rustbininfo/__init__.py
rustbininfo/cache.py
rustbininfo/exception.py
rustbininfo/logger.py
rustbininfo/main.py
rustbininfo/utils.py
rustbininfo/info/compiler.py
rustbininfo/info/dependencies.py
rustbininfo/info/http_client.py
rustbininfo/info/rust_repo_handler.py
rustbininfo/info/models/crate.py
rustbininfo/info/models/github_api.py
rustbininfo/info/models/info.py
rustbininfo/info/models/registry.py
rustbininfo/info/nightly/nightly.py
rustbininfo/info/specifics/mingw.py
rustbininfo-0.7.2.dist-info/METADATA
rustbininfo-0.7.2.dist-info/WHEEL
rustbininfo-0.7.2.dist-info/entry_points.txt
rustbininfo-0.7.2.dist-info/licenses/LICENSE
rustbininfo-0.7.2.dist-info/RECORD
