Metadata-Version: 2.4
Name: rustbininfo
Version: 0.7.2
Summary: Get information about stripped rust executables
Author-email: Nofix <16479266+N0fix@users.noreply.github.com>
License-File: LICENSE
Requires-Python: >=3.10
Requires-Dist: beaker>=1.13.0
Requires-Dist: httpx>=0.28.1
Requires-Dist: pydantic>=2.10.6
Requires-Dist: pytz>=2025.1
Requires-Dist: requests>=2.32.3
Requires-Dist: rich>=13.9.4
Requires-Dist: semver>=3.0.4
Requires-Dist: truststore>=0.10.1
Requires-Dist: xdg-base-dirs>=6.0.2
Requires-Dist: yara-python>=4.5.1
Provides-Extra: gitpython
Requires-Dist: gitpython>=3.1.44; extra == 'gitpython'
